Workbook
Name PrimeRate: Settings!$C$4
Name HomeLoanMargin: Settings!$C$5
Name VehicleLoanMargin: Settings!$C$6
Name EffectiveHomeLoanRate: Settings!$C$8
Name EffectiveVehicleLoanRate: Settings!$C$9
Name EmergencyFundMonths: Settings!$C$11
Name TotalHouseholdIncome: Income!$D$60
Name TotalExpenses: Expenses!$B$124
Name TotalEssentialExpenses: Expenses!$B$126
Name TotalDebtOutstanding: 'Debt Tracker'!$E$26
Name TotalMonthlyDebtPayment: 'Debt Tracker'!$I$26
Name TotalSavings: 'Savings Tracker'!$C$26
Name TotalInvestments: Investments!$D$26
Name CurrentEmergencySavings: 'Emergency Fund'!$C$11

Sheet Dashboard
A1: Personal Finance Dashboard
A2: This dashboard updates automatically from all other sheets. No input needed here.
B4: Total Monthly Income | E4: Total Monthly Expenses | H4: Net Cash Flow
B5: =TotalHouseholdIncome | E5: =TotalExpenses | H5: =TotalHouseholdIncome-TotalExpenses
B7: Total Debt Outstanding | E7: Total Savings | H7: Total Investments
B8: =TotalDebtOutstanding | E8: =TotalSavings | H8: =TotalInvestments
B10: Emergency Fund Status | E10: Savings Rate | H10: Debt-to-Income Ratio
B11: ='Emergency Fund'!C13 | E11: =IF(TotalHouseholdIncome=0,0,(TotalHouseholdIncome-TotalExpenses)/TotalHouseholdIncome) | H11: ='Debt Tracker'!B28
B13: NET WORTH | E13: Assets - Liabilities
B14: =TotalSavings+TotalInvestments-TotalDebtOutstanding
B16: MONTHLY BUDGET vs ACTUAL (Top Categories)
B40: Category | C40: Amount
B41: Income | C41: =TotalHouseholdIncome
B42: Expenses | C42: =TotalExpenses
B43: Net Cash Flow | C43: =TotalHouseholdIncome-TotalExpenses
B44: Debt Payments | C44: =TotalMonthlyDebtPayment
B45: Savings | C45: =TotalSavings
B48: NET WORTH TREND (Monthly Tracking)
B49: Month | C49: Net Worth | D49: Income | E49: Expenses
B50: Jan
B51: Feb
B52: Mar
B53: Apr
B54: May
B55: Jun
B56: Jul
B57: Aug
B58: Sep
B59: Oct
B60: Nov
B61: Dec

Sheet Income
A1: Household Income Tracker
A2: Enter all income sources below. Use the dropdowns for Person and Type. Totals update automatically.
A4: Person | B4: Income Source | C4: Type | D4: Amount (Monthly) | E4: Date | F4: Notes
A57: INCOME SUMMARY
B58: My Total Income | D58: =SUMIFS(D5:D54,A5:A54,"Me")
B59: Wife Total Income | D59: =SUMIFS(D5:D54,A5:A54,"Wife")
B60: Combined Household Income | D60: =SUM(D5:D54)

Sheet Expenses
A1: Monthly Expense Tracker
A2: Log all expenses. Use dropdowns for Category, Fixed/Variable, and Paid By. Summaries below update automatically.
A4: Category | B4: Description | C4: Fixed/Variable | D4: Amount | E4: Date | F4: Paid By | G4: Notes
A107: EXPENSE SUMMARY BY CATEGORY
A108: Category | B108: Total | C108: % of Total
A109: Housing | B109: =SUMIFS(D5:D104,A5:A104,A109) | C109: =IF(B124=0,0,B109/B124)
A110: Transport | B110: =SUMIFS(D5:D104,A5:A104,A110) | C110: =IF(B124=0,0,B110/B124)
A111: Food & Groceries | B111: =SUMIFS(D5:D104,A5:A104,A111) | C111: =IF(B124=0,0,B111/B124)
A112: Insurance | B112: =SUMIFS(D5:D104,A5:A104,A112) | C112: =IF(B124=0,0,B112/B124)
A113: Utilities | B113: =SUMIFS(D5:D104,A5:A104,A113) | C113: =IF(B124=0,0,B113/B124)
A114: Entertainment | B114: =SUMIFS(D5:D104,A5:A104,A114) | C114: =IF(B124=0,0,B114/B124)
A115: Healthcare | B115: =SUMIFS(D5:D104,A5:A104,A115) | C115: =IF(B124=0,0,B115/B124)
A116: Education | B116: =SUMIFS(D5:D104,A5:A104,A116) | C116: =IF(B124=0,0,B116/B124)
A117: Clothing | B117: =SUMIFS(D5:D104,A5:A104,A117) | C117: =IF(B124=0,0,B117/B124)
A118: Personal Care | B118: =SUMIFS(D5:D104,A5:A104,A118) | C118: =IF(B124=0,0,B118/B124)
A119: Debt Payments | B119: =SUMIFS(D5:D104,A5:A104,A119) | C119: =IF(B124=0,0,B119/B124)
A120: Subscriptions | B120: =SUMIFS(D5:D104,A5:A104,A120) | C120: =IF(B124=0,0,B120/B124)
A121: Donations | B121: =SUMIFS(D5:D104,A5:A104,A121) | C121: =IF(B124=0,0,B121/B124)
A122: Childcare | B122: =SUMIFS(D5:D104,A5:A104,A122) | C122: =IF(B124=0,0,B122/B124)
A123: Other | B123: =SUMIFS(D5:D104,A5:A104,A123) | C123: =IF(B124=0,0,B123/B124)
A124: TOTAL EXPENSES | B124: =SUM(D5:D104)
A126: Total Essential Expenses | B126: =SUMIFS(D5:D104,A5:A104,"Housing")+SUMIFS(D5:D104,A5:A104,"Food & Groceries")+SUMIFS(D5:D104,A5:A104,"Utilities")+SUMIFS(D5:D104,A5:A104,"Insurance")+SUMIFS(D5:D104,A5:A104,"Healthcare")+SUMIFS(D5:D104,A5:A104,"Transport")

Sheet Debt Tracker
A1: Debt Tracker
A2: Track all debts below. Interest rate auto-calculates from Prime + Margin unless you override. All calculations are automatic.
A4: Debt Type | B4: Lender | C4: Owner | D4: Original Amount | E4: Outstanding Balance | F4: Rate Mode | G4: Margin (%) | H4: Interest Rate | I4: Monthly Payment | J4: Remaining Term (mo) | K4: Monthly Interest | L4: Total Interest Left | M4: Payoff Progress (%)
H5: =IF(F5="Manual",G5,Settings!$C$4+G5) | K5: =IF(E5=0,0,E5*H5/12) | L5: =IF(J5=0,0,K5*J5) | M5: =IF(D5=0,0,1-(E5/D5))
H6: =IF(F6="Manual",G6,Settings!$C$4+G6) | K6: =IF(E6=0,0,E6*H6/12) | L6: =IF(J6=0,0,K6*J6) | M6: =IF(D6=0,0,1-(E6/D6))
H7: =IF(F7="Manual",G7,Settings!$C$4+G7) | K7: =IF(E7=0,0,E7*H7/12) | L7: =IF(J7=0,0,K7*J7) | M7: =IF(D7=0,0,1-(E7/D7))
H8: =IF(F8="Manual",G8,Settings!$C$4+G8) | K8: =IF(E8=0,0,E8*H8/12) | L8: =IF(J8=0,0,K8*J8) | M8: =IF(D8=0,0,1-(E8/D8))
H9: =IF(F9="Manual",G9,Settings!$C$4+G9) | K9: =IF(E9=0,0,E9*H9/12) | L9: =IF(J9=0,0,K9*J9) | M9: =IF(D9=0,0,1-(E9/D9))
H10: =IF(F10="Manual",G10,Settings!$C$4+G10) | K10: =IF(E10=0,0,E10*H10/12) | L10: =IF(J10=0,0,K10*J10) | M10: =IF(D10=0,0,1-(E10/D10))
H11: =IF(F11="Manual",G11,Settings!$C$4+G11) | K11: =IF(E11=0,0,E11*H11/12) | L11: =IF(J11=0,0,K11*J11) | M11: =IF(D11=0,0,1-(E11/D11))
H12: =IF(F12="Manual",G12,Settings!$C$4+G12) | K12: =IF(E12=0,0,E12*H12/12) | L12: =IF(J12=0,0,K12*J12) | M12: =IF(D12=0,0,1-(E12/D12))
H13: =IF(F13="Manual",G13,Settings!$C$4+G13) | K13: =IF(E13=0,0,E13*H13/12) | L13: =IF(J13=0,0,K13*J13) | M13: =IF(D13=0,0,1-(E13/D13))
H14: =IF(F14="Manual",G14,Settings!$C$4+G14) | K14: =IF(E14=0,0,E14*H14/12) | L14: =IF(J14=0,0,K14*J14) | M14: =IF(D14=0,0,1-(E14/D14))
H15: =IF(F15="Manual",G15,Settings!$C$4+G15) | K15: =IF(E15=0,0,E15*H15/12) | L15: =IF(J15=0,0,K15*J15) | M15: =IF(D15=0,0,1-(E15/D15))
H16: =IF(F16="Manual",G16,Settings!$C$4+G16) | K16: =IF(E16=0,0,E16*H16/12) | L16: =IF(J16=0,0,K16*J16) | M16: =IF(D16=0,0,1-(E16/D16))
... H24: =IF(F24="Manual",G24,Settings!$C$4+G24) | K24: =IF(E24=0,0,E24*H24/12) | L24: =IF(J24=0,0,K24*J24) | M24: =IF(D24=0,0,1-(E24/D24))
A26: TOTALS | D26: =SUM(D5:D24) | E26: =SUM(E5:E24) | I26: =SUM(I5:I24) | K26: =SUM(K5:K24) | L26: =SUM(L5:L24)
A28: Debt-to-Income Ratio | B28: =IF(TotalHouseholdIncome=0,0,I26/TotalHouseholdIncome) | C28: Monthly payments / Monthly income

Sheet Home Loan Calc
A1: Home Loan Calculator
A2: Enter your property details below. The monthly repayment and amortization schedule calculate automatically using the Prime + Margin rate from Settings.
B4: Property Value | C4: 2000000
B5: Loan Amount | C5: 1800000
B6: Loan Term (years) | C6: 20
B7: Start Date | C7: 45292
B8: Interest Rate (Prime + Margin) | C8: =EffectiveHomeLoanRate
B10: Monthly Repayment | C10: =-PMT(C8/12,C6*12,C5)
B11: Total Interest Payable | C11: =C10*C6*12-C5
B12: Total Cost of Property | C12: =C5+C11
B14: AMORTIZATION SCHEDULE
B15: Month | C15: Payment | D15: Principal | E15: Interest | F15: Balance
B16: 1 | C16: =IF(B16>$C$6*12,0,$C$10) | D16: =IF(B16>$C$6*12,0,C16-E16) | E16: =IF(B16>$C$6*12,0,$C$5*$C$8/12) | F16: =IF(B16>$C$6*12,0,$C$5-D16)
B17: 2 | C17: =IF(B17>$C$6*12,0,$C$10) | D17: =IF(B17>$C$6*12,0,C17-E17) | E17: =IF(B17>$C$6*12,0,F16*$C$8/12) | F17: =IF(B17>$C$6*12,0,MAX(0,F16-D17))
B18: 3 | C18: =IF(B18>$C$6*12,0,$C$10) | D18: =IF(B18>$C$6*12,0,C18-E18) | E18: =IF(B18>$C$6*12,0,F17*$C$8/12) | F18: =IF(B18>$C$6*12,0,MAX(0,F17-D18))
B19: 4 | C19: =IF(B19>$C$6*12,0,$C$10) | D19: =IF(B19>$C$6*12,0,C19-E19) | E19: =IF(B19>$C$6*12,0,F18*$C$8/12) | F19: =IF(B19>$C$6*12,0,MAX(0,F18-D19))
B20: 5 | C20: =IF(B20>$C$6*12,0,$C$10) | D20: =IF(B20>$C$6*12,0,C20-E20) | E20: =IF(B20>$C$6*12,0,F19*$C$8/12) | F20: =IF(B20>$C$6*12,0,MAX(0,F19-D20))
B21: 6 | C21: =IF(B21>$C$6*12,0,$C$10) | D21: =IF(B21>$C$6*12,0,C21-E21) | E21: =IF(B21>$C$6*12,0,F20*$C$8/12) | F21: =IF(B21>$C$6*12,0,MAX(0,F20-D21))
B22: 7 | C22: =IF(B22>$C$6*12,0,$C$10) | D22: =IF(B22>$C$6*12,0,C22-E22) | E22: =IF(B22>$C$6*12,0,F21*$C$8/12) | F22: =IF(B22>$C$6*12,0,MAX(0,F21-D22))
B23: 8 | C23: =IF(B23>$C$6*12,0,$C$10) | D23: =IF(B23>$C$6*12,0,C23-E23) | E23: =IF(B23>$C$6*12,0,F22*$C$8/12) | F23: =IF(B23>$C$6*12,0,MAX(0,F22-D23))
B24: 9 | C24: =IF(B24>$C$6*12,0,$C$10) | D24: =IF(B24>$C$6*12,0,C24-E24) | E24: =IF(B24>$C$6*12,0,F23*$C$8/12) | F24: =IF(B24>$C$6*12,0,MAX(0,F23-D24))
B25: 10 | C25: =IF(B25>$C$6*12,0,$C$10) | D25: =IF(B25>$C$6*12,0,C25-E25) | E25: =IF(B25>$C$6*12,0,F24*$C$8/12) | F25: =IF(B25>$C$6*12,0,MAX(0,F24-D25))
B26: 11 | C26: =IF(B26>$C$6*12,0,$C$10) | D26: =IF(B26>$C$6*12,0,C26-E26) | E26: =IF(B26>$C$6*12,0,F25*$C$8/12) | F26: =IF(B26>$C$6*12,0,MAX(0,F25-D26))
B27: 12 | C27: =IF(B27>$C$6*12,0,$C$10) | D27: =IF(B27>$C$6*12,0,C27-E27) | E27: =IF(B27>$C$6*12,0,F26*$C$8/12) | F27: =IF(B27>$C$6*12,0,MAX(0,F26-D27))
B28: 13 | C28: =IF(B28>$C$6*12,0,$C$10) | D28: =IF(B28>$C$6*12,0,C28-E28) | E28: =IF(B28>$C$6*12,0,F27*$C$8/12) | F28: =IF(B28>$C$6*12,0,MAX(0,F27-D28))
... B375: 360 | C375: =IF(B375>$C$6*12,0,$C$10) | D375: =IF(B375>$C$6*12,0,C375-E375) | E375: =IF(B375>$C$6*12,0,F374*$C$8/12) | F375: =IF(B375>$C$6*12,0,MAX(0,F374-D375))

Sheet Vehicle Loan Calc
A1: Vehicle Loan Calculator
A2: Enter vehicle details. Monthly repayment uses Prime + Vehicle Margin from Settings. Depreciation estimate included.
B4: Vehicle Purchase Price | C4: 450000
B5: Loan Amount | C5: 400000
B6: Loan Term (years) | C6: 5
B7: Start Date | C7: 45292
B8: Annual Depreciation Rate (%) | C8: 0.15
B9: Interest Rate (Prime + Margin) | C9: =EffectiveVehicleLoanRate
B11: Monthly Repayment | C11: =-PMT(C9/12,C6*12,C5)
B12: Total Interest Payable | C12: =C11*C6*12-C5
B13: Total Cost of Vehicle | C13: =C5+C12
B15: DEPRECIATION SCHEDULE
B16: Year | C16: Estimated Value | D16: Depreciation Amount
B17: 1 | C17: =$C$4*(1-$C$8)^B17 | D17: =$C$4-C17
B18: 2 | C18: =$C$4*(1-$C$8)^B18 | D18: =C17-C18
B19: 3 | C19: =$C$4*(1-$C$8)^B19 | D19: =C18-C19
B20: 4 | C20: =$C$4*(1-$C$8)^B20 | D20: =C19-C20
B21: 5 | C21: =$C$4*(1-$C$8)^B21 | D21: =C20-C21
B22: 6 | C22: =$C$4*(1-$C$8)^B22 | D22: =C21-C22
B23: 7 | C23: =$C$4*(1-$C$8)^B23 | D23: =C22-C23
B24: 8 | C24: =$C$4*(1-$C$8)^B24 | D24: =C23-C24
B25: 9 | C25: =$C$4*(1-$C$8)^B25 | D25: =C24-C25
B26: 10 | C26: =$C$4*(1-$C$8)^B26 | D26: =C25-C26
B28: LOAN AMORTIZATION SCHEDULE
B29: Month | C29: Payment | D29: Principal | E29: Interest | F29: Balance
B30: 1 | C30: =IF(B30>$C$6*12,0,$C$11) | D30: =IF(B30>$C$6*12,0,C30-E30) | E30: =IF(B30>$C$6*12,0,$C$5*$C$9/12) | F30: =IF(B30>$C$6*12,0,$C$5-D30)
B31: 2 | C31: =IF(B31>$C$6*12,0,$C$11) | D31: =IF(B31>$C$6*12,0,C31-E31) | E31: =IF(B31>$C$6*12,0,F30*$C$9/12) | F31: =IF(B31>$C$6*12,0,MAX(0,F30-D31))
B32: 3 | C32: =IF(B32>$C$6*12,0,$C$11) | D32: =IF(B32>$C$6*12,0,C32-E32) | E32: =IF(B32>$C$6*12,0,F31*$C$9/12) | F32: =IF(B32>$C$6*12,0,MAX(0,F31-D32))
B33: 4 | C33: =IF(B33>$C$6*12,0,$C$11) | D33: =IF(B33>$C$6*12,0,C33-E33) | E33: =IF(B33>$C$6*12,0,F32*$C$9/12) | F33: =IF(B33>$C$6*12,0,MAX(0,F32-D33))
B34: 5 | C34: =IF(B34>$C$6*12,0,$C$11) | D34: =IF(B34>$C$6*12,0,C34-E34) | E34: =IF(B34>$C$6*12,0,F33*$C$9/12) | F34: =IF(B34>$C$6*12,0,MAX(0,F33-D34))
B35: 6 | C35: =IF(B35>$C$6*12,0,$C$11) | D35: =IF(B35>$C$6*12,0,C35-E35) | E35: =IF(B35>$C$6*12,0,F34*$C$9/12) | F35: =IF(B35>$C$6*12,0,MAX(0,F34-D35))
B36: 7 | C36: =IF(B36>$C$6*12,0,$C$11) | D36: =IF(B36>$C$6*12,0,C36-E36) | E36: =IF(B36>$C$6*12,0,F35*$C$9/12) | F36: =IF(B36>$C$6*12,0,MAX(0,F35-D36))
B37: 8 | C37: =IF(B37>$C$6*12,0,$C$11) | D37: =IF(B37>$C$6*12,0,C37-E37) | E37: =IF(B37>$C$6*12,0,F36*$C$9/12) | F37: =IF(B37>$C$6*12,0,MAX(0,F36-D37))
B38: 9 | C38: =IF(B38>$C$6*12,0,$C$11) | D38: =IF(B38>$C$6*12,0,C38-E38) | E38: =IF(B38>$C$6*12,0,F37*$C$9/12) | F38: =IF(B38>$C$6*12,0,MAX(0,F37-D38))
B39: 10 | C39: =IF(B39>$C$6*12,0,$C$11) | D39: =IF(B39>$C$6*12,0,C39-E39) | E39: =IF(B39>$C$6*12,0,F38*$C$9/12) | F39: =IF(B39>$C$6*12,0,MAX(0,F38-D39))
B40: 11 | C40: =IF(B40>$C$6*12,0,$C$11) | D40: =IF(B40>$C$6*12,0,C40-E40) | E40: =IF(B40>$C$6*12,0,F39*$C$9/12) | F40: =IF(B40>$C$6*12,0,MAX(0,F39-D40))
B41: 12 | C41: =IF(B41>$C$6*12,0,$C$11) | D41: =IF(B41>$C$6*12,0,C41-E41) | E41: =IF(B41>$C$6*12,0,F40*$C$9/12) | F41: =IF(B41>$C$6*12,0,MAX(0,F40-D41))
B42: 13 | C42: =IF(B42>$C$6*12,0,$C$11) | D42: =IF(B42>$C$6*12,0,C42-E42) | E42: =IF(B42>$C$6*12,0,F41*$C$9/12) | F42: =IF(B42>$C$6*12,0,MAX(0,F41-D42))
... B113: 84 | C113: =IF(B113>$C$6*12,0,$C$11) | D113: =IF(B113>$C$6*12,0,C113-E113) | E113: =IF(B113>$C$6*12,0,F112*$C$9/12) | F113: =IF(B113>$C$6*12,0,MAX(0,F112-D113))

Sheet Savings Tracker
A1: Savings Tracker
A2: Track all savings accounts. Goal progress and time-to-goal calculate automatically.
A4: Account Name | B4: Type | C4: Current Balance | D4: Monthly Contribution | E4: Target Amount | F4: % of Goal | G4: Remaining to Goal | H4: Months to Goal
F5: =IF(E5=0,0,MIN(1,C5/E5)) | G5: =IF(E5=0,0,MAX(0,E5-C5)) | H5: =IF(OR(D5=0,G5<=0),"N/A",ROUNDUP(G5/D5,0))
F6: =IF(E6=0,0,MIN(1,C6/E6)) | G6: =IF(E6=0,0,MAX(0,E6-C6)) | H6: =IF(OR(D6=0,G6<=0),"N/A",ROUNDUP(G6/D6,0))
F7: =IF(E7=0,0,MIN(1,C7/E7)) | G7: =IF(E7=0,0,MAX(0,E7-C7)) | H7: =IF(OR(D7=0,G7<=0),"N/A",ROUNDUP(G7/D7,0))
F8: =IF(E8=0,0,MIN(1,C8/E8)) | G8: =IF(E8=0,0,MAX(0,E8-C8)) | H8: =IF(OR(D8=0,G8<=0),"N/A",ROUNDUP(G8/D8,0))
F9: =IF(E9=0,0,MIN(1,C9/E9)) | G9: =IF(E9=0,0,MAX(0,E9-C9)) | H9: =IF(OR(D9=0,G9<=0),"N/A",ROUNDUP(G9/D9,0))
F10: =IF(E10=0,0,MIN(1,C10/E10)) | G10: =IF(E10=0,0,MAX(0,E10-C10)) | H10: =IF(OR(D10=0,G10<=0),"N/A",ROUNDUP(G10/D10,0))
F11: =IF(E11=0,0,MIN(1,C11/E11)) | G11: =IF(E11=0,0,MAX(0,E11-C11)) | H11: =IF(OR(D11=0,G11<=0),"N/A",ROUNDUP(G11/D11,0))
F12: =IF(E12=0,0,MIN(1,C12/E12)) | G12: =IF(E12=0,0,MAX(0,E12-C12)) | H12: =IF(OR(D12=0,G12<=0),"N/A",ROUNDUP(G12/D12,0))
F13: =IF(E13=0,0,MIN(1,C13/E13)) | G13: =IF(E13=0,0,MAX(0,E13-C13)) | H13: =IF(OR(D13=0,G13<=0),"N/A",ROUNDUP(G13/D13,0))
F14: =IF(E14=0,0,MIN(1,C14/E14)) | G14: =IF(E14=0,0,MAX(0,E14-C14)) | H14: =IF(OR(D14=0,G14<=0),"N/A",ROUNDUP(G14/D14,0))
F15: =IF(E15=0,0,MIN(1,C15/E15)) | G15: =IF(E15=0,0,MAX(0,E15-C15)) | H15: =IF(OR(D15=0,G15<=0),"N/A",ROUNDUP(G15/D15,0))
F16: =IF(E16=0,0,MIN(1,C16/E16)) | G16: =IF(E16=0,0,MAX(0,E16-C16)) | H16: =IF(OR(D16=0,G16<=0),"N/A",ROUNDUP(G16/D16,0))
... F24: =IF(E24=0,0,MIN(1,C24/E24)) | G24: =IF(E24=0,0,MAX(0,E24-C24)) | H24: =IF(OR(D24=0,G24<=0),"N/A",ROUNDUP(G24/D24,0))
A26: TOTALS | C26: =SUM(C5:C24) | D26: =SUM(D5:D24) | E26: =SUM(E5:E24)

Sheet Investments
A1: Investment Portfolio Tracker
A2: Track all investments. Gain/loss and weighted return calculate automatically.
A4: Investment Type | B4: Platform | C4: Initial Investment | D4: Current Value | E4: Monthly Contribution | F4: Expected Return (% p.a.) | G4: Gain / Loss | H4: Gain / Loss (%) | I4: Notes
G5: =IF(C5=0,0,D5-C5) | H5: =IF(C5=0,0,G5/C5)
G6: =IF(C6=0,0,D6-C6) | H6: =IF(C6=0,0,G6/C6)
G7: =IF(C7=0,0,D7-C7) | H7: =IF(C7=0,0,G7/C7)
G8: =IF(C8=0,0,D8-C8) | H8: =IF(C8=0,0,G8/C8)
G9: =IF(C9=0,0,D9-C9) | H9: =IF(C9=0,0,G9/C9)
G10: =IF(C10=0,0,D10-C10) | H10: =IF(C10=0,0,G10/C10)
G11: =IF(C11=0,0,D11-C11) | H11: =IF(C11=0,0,G11/C11)
G12: =IF(C12=0,0,D12-C12) | H12: =IF(C12=0,0,G12/C12)
G13: =IF(C13=0,0,D13-C13) | H13: =IF(C13=0,0,G13/C13)
G14: =IF(C14=0,0,D14-C14) | H14: =IF(C14=0,0,G14/C14)
G15: =IF(C15=0,0,D15-C15) | H15: =IF(C15=0,0,G15/C15)
G16: =IF(C16=0,0,D16-C16) | H16: =IF(C16=0,0,G16/C16)
... G24: =IF(C24=0,0,D24-C24) | H24: =IF(C24=0,0,G24/C24)
A26: TOTALS | C26: =SUM(C5:C24) | D26: =SUM(D5:D24) | E26: =SUM(E5:E24) | G26: =SUM(G5:G24)
A28: Weighted Expected Return | B28: =IF(D26=0,0,SUMPRODUCT(D5:D24,F5:F24)/D26)

Sheet Emergency Fund
A1: Emergency Fund Tracker
A2: Your emergency fund target is calculated from essential expenses (linked from Expenses sheet). Update your current emergency savings below.
B4: Monthly Essential Expenses | C4: =TotalEssentialExpenses | D4: Linked from Expenses sheet
B5: Target Months of Expenses | C5: =EmergencyFundMonths | D5: Set in Settings sheet
B7: Emergency Fund Target (3 months) | C7: =C4*3
B8: Emergency Fund Target (6 months) | C8: =C4*6
B9: Emergency Fund Target (custom from Settings) | C9: =C4*C5
B11: Current Emergency Savings | C11: 0 | D11: Enter your current emergency fund balance
B13: % of Target Reached | C13: =IF(C9=0,0,C11/C9)
B14: Months of Expenses Covered | C14: =IF(C4=0,0,ROUND(C11/C4,1))
B15: Shortfall / Surplus | C15: =C11-C9
B17: FUND STATUS | C17: =IF(C14>=6,"FULLY FUNDED",IF(C14>=3,"ON TRACK (3-6 months)","UNDERFUNDED"))

Sheet Settings
A1: Settings & Configuration
A2: Update the values below. All loan calculations reference these settings automatically.
B4: Namibian Prime Lending Rate (%) | C4: 0.1125 | D4: Currently 11.25% as of 2024
B5: Home Loan Margin (%) | C5: 0.02 | D5: Margin above prime for home loan
B6: Vehicle Loan Margin (%) | C6: 0.025 | D6: Margin above prime for vehicle loan
B8: Effective Home Loan Rate | C8: =C4+C5 | D8: =Prime + Home Loan Margin
B9: Effective Vehicle Loan Rate | C9: =C4+C6 | D9: =Prime + Vehicle Loan Margin
B11: Emergency Fund Target (months) | C11: 6 | D11: Recommended: 3-6 months
B13: Currency | C13: NAD (N$)
B15: COLOR LEGEND
B16: Input Cell (you type here)
B17: Formula / Calculated Cell (auto)
B18: Header Row
